Workbook

Sheet Summary
A1: Universe summary
A2: All counts are live formulas on the Universe tab - update coverage there and these refresh.
A4: Total names | B4: =COUNTA(Universe!$A$5:$A$241) -> 237
A5: Coverage verified as zero | B5: =COUNTIF(Universe!$H$5:$H$241,"0 (checked)") -> 10
A6: Coverage still unverified | B6: =COUNTIF(Universe!$H$5:$H$241,"Unverified") -> 223
A7: Tradable names (>= $50M) | B7: =SUM(Universe!$K$5:$K$241) -> 207
A8: Combined market cap ($M) | B8: =SUM(Universe!$C$5:$C$241) -> 53091.32
A10: By archetype
A11: Archetype | B11: Names | C11: Mkt cap ($M) | D11: Avg priority
A12: Community bank | B12: =COUNTIF(Universe!$D$5:$D$241,A12) -> 110 | C12: =SUMIF(Universe!$D$5:$D$241,A12,Universe!$C$5:$C$241) -> 27850.14 | D12: =AVERAGEIF(Universe!$D$5:$D$241,A12,Universe!$M$5:$M$241) -> 6.9727273
A13: Regulated utility | B13: =COUNTIF(Universe!$D$5:$D$241,A13) -> 6 | C13: =SUMIF(Universe!$D$5:$D$241,A13,Universe!$C$5:$C$241) -> 1965.28 | D13: =AVERAGEIF(Universe!$D$5:$D$241,A13,Universe!$M$5:$M$241) -> 7
A14: Energy project developer | B14: =COUNTIF(Universe!$D$5:$D$241,A14) -> 4 | C14: =SUMIF(Universe!$D$5:$D$241,A14,Universe!$C$5:$C$241) -> 724.41 | D14: =AVERAGEIF(Universe!$D$5:$D$241,A14,Universe!$M$5:$M$241) -> 6.5
A15: Land / entitlement developer | B15: =COUNTIF(Universe!$D$5:$D$241,A15) -> 14 | C15: =SUMIF(Universe!$D$5:$D$241,A15,Universe!$C$5:$C$241) -> 3428.32 | D15: =AVERAGEIF(Universe!$D$5:$D$241,A15,Universe!$M$5:$M$241) -> 8.0357143
A16: Property owner (commercial) | B16: =COUNTIF(Universe!$D$5:$D$241,A16) -> 18 | C16: =SUMIF(Universe!$D$5:$D$241,A16,Universe!$C$5:$C$241) -> 3380.81 | D16: =AVERAGEIF(Universe!$D$5:$D$241,A16,Universe!$M$5:$M$241) -> 5.7777778
A17: Apartment owner | B17: =COUNTIF(Universe!$D$5:$D$241,A17) -> 8 | C17: =SUMIF(Universe!$D$5:$D$241,A17,Universe!$C$5:$C$241) -> 1908.84 | D17: =AVERAGEIF(Universe!$D$5:$D$241,A17,Universe!$M$5:$M$241) -> 8
A18: RE transaction platform | B18: =COUNTIF(Universe!$D$5:$D$241,A18) -> 3 | C18: =SUMIF(Universe!$D$5:$D$241,A18,Universe!$C$5:$C$241) -> 156.94 | D18: =AVERAGEIF(Universe!$D$5:$D$241,A18,Universe!$M$5:$M$241) -> 5.3333333
A19: Hotel owner | B19: =COUNTIF(Universe!$D$5:$D$241,A19) -> 4 | C19: =SUMIF(Universe!$D$5:$D$241,A19,Universe!$C$5:$C$241) -> 223.46 | D19: =AVERAGEIF(Universe!$D$5:$D$241,A19,Universe!$M$5:$M$241) -> 6.75
A20: Farmland / water rights | B20: =COUNTIF(Universe!$D$5:$D$241,A20) -> 3 | C20: =SUMIF(Universe!$D$5:$D$241,A20,Universe!$C$5:$C$241) -> 1289.16 | D20: =AVERAGEIF(Universe!$D$5:$D$241,A20,Universe!$M$5:$M$241) -> 6
A21: Regional gaming / racing | B21: =COUNTIF(Universe!$D$5:$D$241,A21) -> 3 | C21: =SUMIF(Universe!$D$5:$D$241,A21,Universe!$C$5:$C$241) -> 161.84 | D21: =AVERAGEIF(Universe!$D$5:$D$241,A21,Universe!$M$5:$M$241) -> 8
A22: Oil & gas producer / royalty | B22: =COUNTIF(Universe!$D$5:$D$241,A22) -> 21 | C22: =SUMIF(Universe!$D$5:$D$241,A22,Universe!$C$5:$C$241) -> 2666.23 | D22: =AVERAGEIF(Universe!$D$5:$D$241,A22,Universe!$M$5:$M$241) -> 6.7142857
A23: Midstream / energy infrastructure | B23: =COUNTIF(Universe!$D$5:$D$241,A23) -> 4 | C23: =SUMIF(Universe!$D$5:$D$241,A23,Universe!$C$5:$C$241) -> 621.79 | D23: =AVERAGEIF(Universe!$D$5:$D$241,A23,Universe!$M$5:$M$241) -> 5.75
... A30: Government-funded services | B30: =COUNTIF(Universe!$D$5:$D$241,A30) -> 3 | C30: =SUMIF(Universe!$D$5:$D$241,A30,Universe!$C$5:$C$241) -> 378.93 | D30: =AVERAGEIF(Universe!$D$5:$D$241,A30,Universe!$M$5:$M$241) -> 6.6666667
A31: Total | B31: =SUM(B12:B30) -> 237 | C31: =SUM(C12:C30) -> 53091.32

Sheet Universe
A1: Microcap local-government universe - 237 US-listed names under $500M
A2: Built from StockAnalysis.com industry lists (Oct 16, 2026), filtered to market cap < $500M and to companies where a local/state government decision or a public dataset plausibly drives fundamentals. Foreign-operating, shell and pure consumer/tech names removed. Sorted by Priority (highest first). Use the filters in row 4.
A4: Ticker | B4: Company | C4: Mkt cap ($M) | D4: Archetype | E4: Local-gov driver | F4: Public data to ingest | G4: Note | H4: Analyst coverage | I4: Local-gov intensity (1-3) | J4: Data edge (1-3) | K4: Tradable (>= $50M) | L4: Coverage pts | M4: Priority | N4: Size band
A5: TRC | B5: Tejon Ranch | C5: 437.21 | D5: Land / entitlement developer | E5: Value unlocked by entitlements, zoning, plats and permits on specific parcels | F5: Planning commission & council agendas; plat approvals; Census BPS; county deed and assessor records | G5: Kern/LA County entitlements; CEQA litigation; water | H5: 0 (checked) | I5: 3 | J5: 3 | K5: =IF(C5>=50,1,0) -> 1 | L5: =IF(H5="0 (checked)",2,IF(H5="Unverified",1,IF(H5="1 (checked)",0.5,0))) -> 2 | M5: =I5+J5+K5+L5 -> 9 | N5: =IF(C5<25,"Nano (<$25M)",IF(C5<100,"$25-100M",IF(C5<250,"$100-250M","$250-500M"))) -> $250-500M
A6: MLP | B6: Maui Land & Pineapple | C6: 295.9 | D6: Land / entitlement developer | E6: Value unlocked by entitlements, zoning, plats and permits on specific parcels | F6: Planning commission & council agendas; plat approvals; Census BPS; county deed and assessor records | G6: Maui County & state water decisions; water-asset strategic review | H6: 0 (checked) | I6: 3 | J6: 3 | K6: =IF(C6>=50,1,0) -> 1 | L6: =IF(H6="0 (checked)",2,IF(H6="Unverified",1,IF(H6="1 (checked)",0.5,0))) -> 2 | M6: =I6+J6+K6+L6 -> 9 | N6: =IF(C6<25,"Nano (<$25M)",IF(C6<100,"$25-100M",IF(C6<250,"$100-250M","$250-500M"))) -> $250-500M
A7: CPHC | B7: Canterbury Park | C7: 81.64 | D7: Regional gaming / racing | E7: State gaming & racing commissions license and tax; local approvals for expansions | F7: Monthly state gaming-revenue reports by property; racing commission minutes; city development agendas | G7: Shakopee TIF; MN Racing Commission; sports-betting bills | H7: 0 (checked) | I7: 3 | J7: 3 | K7: =IF(C7>=50,1,0) -> 1 | L7: =IF(H7="0 (checked)",2,IF(H7="Unverified",1,IF(H7="1 (checked)",0.5,0))) -> 2 | M7: =I7+J7+K7+L7 -> 9 | N7: =IF(C7<25,"Nano (<$25M)",IF(C7<100,"$25-100M",IF(C7<250,"$100-250M","$250-500M"))) -> $25-100M
A8: SDHC | B8: Smith Douglas Homes | C8: 497.1 | D8: Land / entitlement developer | E8: Value unlocked by entitlements, zoning, plats and permits on specific parcels | F8: Planning commission & council agendas; plat approvals; Census BPS; county deed and assessor records | G8: Southeast homebuilder - lot approvals & permits | H8: Unverified | I8: 3 | J8: 3 | K8: =IF(C8>=50,1,0) -> 1 | L8: =IF(H8="0 (checked)",2,IF(H8="Unverified",1,IF(H8="1 (checked)",0.5,0))) -> 1 | M8: =I8+J8+K8+L8 -> 8 | N8: =IF(C8<25,"Nano (<$25M)",IF(C8<100,"$25-100M",IF(C8<250,"$100-250M","$250-500M"))) -> $250-500M
A9: AII | B9: American Integrity Insurance | C9: 488.46 | D9: State-regulated P&C insurer | E9: State insurance departments approve rates; catastrophe reforms in specific states | F9: SERFF rate filings; state insurance dept market-share and complaint data | G9: Florida OIR | H9: Unverified | I9: 3 | J9: 3 | K9: =IF(C9>=50,1,0) -> 1 | L9: =IF(H9="0 (checked)",2,IF(H9="Unverified",1,IF(H9="1 (checked)",0.5,0))) -> 1 | M9: =I9+J9+K9+L9 -> 8 | N9: =IF(C9<25,"Nano (<$25M)",IF(C9<100,"$25-100M",IF(C9<250,"$100-250M","$250-500M"))) -> $250-500M
A10: NXRT | B10: NexPoint Residential Trust | C10: 469.19 | D10: Apartment owner | E10: Rents shaped by local rent rules and new-supply permits in specific metros | F10: Local rent boards (e.g., NYC Rent Guidelines Board); multifamily permits; eviction filings; property-tax assessments | H10: Unverified | I10: 3 | J10: 3 | K10: =IF(C10>=50,1,0) -> 1 | L10: =IF(H10="0 (checked)",2,IF(H10="Unverified",1,IF(H10="1 (checked)",0.5,0))) -> 1 | M10: =I10+J10+K10+L10 -> 8 | N10: =IF(C10<25,"Nano (<$25M)",IF(C10<100,"$25-100M",IF(C10<250,"$100-250M","$250-500M"))) -> $250-500M
A11: BBCP | B11: Concrete Pumping | C11: 457.57 | D11: Public-works contractor | E11: Revenue won through state DOT, municipal and utility contract lettings | F11: State DOT bid lettings & awards; municipal procurement portals; utility capex filings | H11: Unverified | I11: 3 | J11: 3 | K11: =IF(C11>=50,1,0) -> 1 | L11: =IF(H11="0 (checked)",2,IF(H11="Unverified",1,IF(H11="1 (checked)",0.5,0))) -> 1 | M11: =I11+J11+K11+L11 -> 8 | N11: =IF(C11<25,"Nano (<$25M)",IF(C11<100,"$25-100M",IF(C11<250,"$100-250M","$250-500M"))) -> $250-500M
A12: TCI | B12: Transcontinental Realty Investors | C12: 431.42 | D12: Land / entitlement developer | E12: Value unlocked by entitlements, zoning, plats and permits on specific parcels | F12: Planning commission & council agendas; plat approvals; Census BPS; county deed and assessor records | G12: Texas land & apartments | H12: Unverified | I12: 3 | J12: 3 | K12: =IF(C12>=50,1,0) -> 1 | L12: =IF(H12="0 (checked)",2,IF(H12="Unverified",1,IF(H12="1 (checked)",0.5,0))) -> 1 | M12: =I12+J12+K12+L12 -> 8 | N12: =IF(C12<25,"Nano (<$25M)",IF(C12<100,"$25-100M",IF(C12<250,"$100-250M","$250-500M"))) -> $250-500M
A13: ACIC | B13: American Coastal Insurance | C13: 421.86 | D13: State-regulated P&C insurer | E13: State insurance departments approve rates; catastrophe reforms in specific states | F13: SERFF rate filings; state insurance dept market-share and complaint data | G13: Florida OIR | H13: Unverified | I13: 3 | J13: 3 | K13: =IF(C13>=50,1,0) -> 1 | L13: =IF(H13="0 (checked)",2,IF(H13="Unverified",1,IF(H13="1 (checked)",0.5,0))) -> 1 | M13: =I13+J13+K13+L13 -> 8 | N13: =IF(C13<25,"Nano (<$25M)",IF(C13<100,"$25-100M",IF(C13<250,"$100-250M","$250-500M"))) -> $250-500M
A14: CYH | B14: Community Health Systems | C14: 405.23 | D14: Healthcare facility operator | E14: State certificate-of-need, Medicaid rates and supplemental payments | F14: State CON dockets; Medicaid fee schedules; CMS hospital cost reports | G14: State CON & Medicaid supplemental payments | H14: Unverified | I14: 3 | J14: 3 | K14: =IF(C14>=50,1,0) -> 1 | L14: =IF(H14="0 (checked)",2,IF(H14="Unverified",1,IF(H14="1 (checked)",0.5,0))) -> 1 | M14: =I14+J14+K14+L14 -> 8 | N14: =IF(C14<25,"Nano (<$25M)",IF(C14<100,"$25-100M",IF(C14<250,"$100-250M","$250-500M"))) -> $250-500M
A15: GBLI | B15: Global Indemnity | C15: 371.64 | D15: State-regulated P&C insurer | E15: State insurance departments approve rates; catastrophe reforms in specific states | F15: SERFF rate filings; state insurance dept market-share and complaint data | H15: Unverified | I15: 3 | J15: 3 | K15: =IF(C15>=50,1,0) -> 1 | L15: =IF(H15="0 (checked)",2,IF(H15="Unverified",1,IF(H15="1 (checked)",0.5,0))) -> 1 | M15: =I15+J15+K15+L15 -> 8 | N15: =IF(C15<25,"Nano (<$25M)",IF(C15<100,"$25-100M",IF(C15<250,"$100-250M","$250-500M"))) -> $250-500M
A16: BSRT | B16: BSR REIT | C16: 358.72 | D16: Apartment owner | E16: Rents shaped by local rent rules and new-supply permits in specific metros | F16: Local rent boards (e.g., NYC Rent Guidelines Board); multifamily permits; eviction filings; property-tax assessments | G16: Sunbelt apartments | H16: Unverified | I16: 3 | J16: 3 | K16: =IF(C16>=50,1,0) -> 1 | L16: =IF(H16="0 (checked)",2,IF(H16="Unverified",1,IF(H16="1 (checked)",0.5,0))) -> 1 | M16: =I16+J16+K16+L16 -> 8 | N16: =IF(C16<25,"Nano (<$25M)",IF(C16<100,"$25-100M",IF(C16<250,"$100-250M","$250-500M"))) -> $250-500M
A17: ORN | B17: Orion Group Holdings | C17: 345.02 | D17: Public-works contractor | E17: Revenue won through state DOT, municipal and utility contract lettings | F17: State DOT bid lettings & awards; municipal procurement portals; utility capex filings | G17: Marine/port public works | H17: Unverified | I17: 3 | J17: 3 | K17: =IF(C17>=50,1,0) -> 1 | L17: =IF(H17="0 (checked)",2,IF(H17="Unverified",1,IF(H17="1 (checked)",0.5,0))) -> 1 | M17: =I17+J17+K17+L17 -> 8 | N17: =IF(C17<25,"Nano (<$25M)",IF(C17<100,"$25-100M",IF(C17<250,"$100-250M","$250-500M"))) -> $250-500M
A18: FIP | B18: FTAI Infrastructure | C18: 321.45 | D18: Land / entitlement developer | E18: Value unlocked by entitlements, zoning, plats and permits on specific parcels | F18: Planning commission & council agendas; plat approvals; Census BPS; county deed and assessor records | G18: Port/terminal and power assets - local and state permits | H18: Unverified | I18: 3 | J18: 3 | K18: =IF(C18>=50,1,0) -> 1 | L18: =IF(H18="0 (checked)",2,IF(H18="Unverified",1,IF(H18="1 (checked)",0.5,0))) -> 1 | M18: =I18+J18+K18+L18 -> 8 | N18: =IF(C18<25,"Nano (<$25M)",IF(C18<100,"$25-100M",IF(C18<250,"$100-250M","$250-500M"))) -> $250-500M
A19: NODK | B19: NI Holdings | C19: 305.66 | D19: State-regulated P&C insurer | E19: State insurance departments approve rates; catastrophe reforms in specific states | F19: SERFF rate filings; state insurance dept market-share and complaint data | G19: North Dakota | H19: Unverified | I19: 3 | J19: 3 | K19: =IF(C19>=50,1,0) -> 1 | L19: =IF(H19="0 (checked)",2,IF(H19="Unverified",1,IF(H19="1 (checked)",0.5,0))) -> 1 | M19: =I19+J19+K19+L19 -> 8 | N19: =IF(C19<25,"Nano (<$25M)",IF(C19<100,"$25-100M",IF(C19<250,"$100-250M","$250-500M"))) -> $250-500M
A20: ARL | B20: American Realty Investors | C20: 293.16 | D20: Land / entitlement developer | E20: Value unlocked by entitlements, zoning, plats and permits on specific parcels | F20: Planning commission & council agendas; plat approvals; Census BPS; county deed and assessor records | G20: Parent of TCI | H20: Unverified | I20: 3 | J20: 3 | K20: =IF(C20>=50,1,0) -> 1 | L20: =IF(H20="0 (checked)",2,IF(H20="Unverified",1,IF(H20="1 (checked)",0.5,0))) -> 1 | M20: =I20+J20+K20+L20 -> 8 | N20: =IF(C20<25,"Nano (<$25M)",IF(C20<100,"$25-100M",IF(C20<250,"$100-250M","$250-500M"))) -> $250-500M
A21: MTRX | B21: Matrix Service | C21: 283.49 | D21: Public-works contractor | E21: Revenue won through state DOT, municipal and utility contract lettings | F21: State DOT bid lettings & awards; municipal procurement portals; utility capex filings | H21: Unverified | I21: 3 | J21: 3 | K21: =IF(C21>=50,1,0) -> 1 | L21: =IF(H21="0 (checked)",2,IF(H21="Unverified",1,IF(H21="1 (checked)",0.5,0))) -> 1 | M21: =I21+J21+K21+L21 -> 8 | N21: =IF(C21<25,"Nano (<$25M)",IF(C21<100,"$25-100M",IF(C21<250,"$100-250M","$250-500M"))) -> $250-500M
A22: PCYO | B22: Pure Cycle | C22: 266.03 | D22: Regulated utility | E22: State commission sets rates; customer additions come from local development approvals | F22: State PUC/SCC rate dockets; county subdivision approvals; Census Building Permits Survey | G22: Sky Ranch plats/permits; activist proxy contest (Aug 2026) | H22: 0 (checked) | I22: 3 | J22: 2 | K22: =IF(C22>=50,1,0) -> 1 | L22: =IF(H22="0 (checked)",2,IF(H22="Unverified",1,IF(H22="1 (checked)",0.5,0))) -> 2 | M22: =I22+J22+K22+L22 -> 8 | N22: =IF(C22<25,"Nano (<$25M)",IF(C22<100,"$25-100M",IF(C22<250,"$100-250M","$250-500M"))) -> $250-500M
A23: BRT | B23: BRT Apartments | C23: 256.81 | D23: Apartment owner | E23: Rents shaped by local rent rules and new-supply permits in specific metros | F23: Local rent boards (e.g., NYC Rent Guidelines Board); multifamily permits; eviction filings; property-tax assessments | H23: Unverified | I23: 3 | J23: 3 | K23: =IF(C23>=50,1,0) -> 1 | L23: =IF(H23="0 (checked)",2,IF(H23="Unverified",1,IF(H23="1 (checked)",0.5,0))) -> 1 | M23: =I23+J23+K23+L23 -> 8 | N23: =IF(C23<25,"Nano (<$25M)",IF(C23<100,"$25-100M",IF(C23<250,"$100-250M","$250-500M"))) -> $250-500M
A24: KINS | B24: Kingstone Companies | C24: 254.49 | D24: State-regulated P&C insurer | E24: State insurance departments approve rates; catastrophe reforms in specific states | F24: SERFF rate filings; state insurance dept market-share and complaint data | G24: New York DFS | H24: Unverified | I24: 3 | J24: 3 | K24: =IF(C24>=50,1,0) -> 1 | L24: =IF(H24="0 (checked)",2,IF(H24="Unverified",1,IF(H24="1 (checked)",0.5,0))) -> 1 | M24: =I24+J24+K24+L24 -> 8 | N24: =IF(C24<25,"Nano (<$25M)",IF(C24<100,"$25-100M",IF(C24<250,"$100-250M","$250-500M"))) -> $250-500M
A25: AIV | B25: Aimco | C25: 253.83 | D25: Apartment owner | E25: Rents shaped by local rent rules and new-supply permits in specific metros | F25: Local rent boards (e.g., NYC Rent Guidelines Board); multifamily permits; eviction filings; property-tax assessments | H25: Unverified | I25: 3 | J25: 3 | K25: =IF(C25>=50,1,0) -> 1 | L25: =IF(H25="0 (checked)",2,IF(H25="Unverified",1,IF(H25="1 (checked)",0.5,0))) -> 1 | M25: =I25+J25+K25+L25 -> 8 | N25: =IF(C25<25,"Nano (<$25M)",IF(C25<100,"$25-100M",IF(C25<250,"$100-250M","$250-500M"))) -> $250-500M
A26: LMNR | B26: Limoneira | C26: 213.6 | D26: Land / entitlement developer | E26: Value unlocked by entitlements, zoning, plats and permits on specific parcels | F26: Planning commission & council agendas; plat approvals; Census BPS; county deed and assessor records | G26: Santa Paula, CA housing development & water | H26: Unverified | I26: 3 | J26: 3 | K26: =IF(C26>=50,1,0) -> 1 | L26: =IF(H26="0 (checked)",2,IF(H26="Unverified",1,IF(H26="1 (checked)",0.5,0))) -> 1 | M26: =I26+J26+K26+L26 -> 8 | N26: =IF(C26<25,"Nano (<$25M)",IF(C26<100,"$25-100M",IF(C26<250,"$100-250M","$250-500M"))) -> $100-250M
A27: CHCI | B27: Comstock Holding | C27: 187.44 | D27: Land / entitlement developer | E27: Value unlocked by entitlements, zoning, plats and permits on specific parcels | F27: Planning commission & council agendas; plat approvals; Census BPS; county deed and assessor records | G27: Reston/Loudoun, VA transit-oriented development | H27: Unverified | I27: 3 | J27: 3 | K27: =IF(C27>=50,1,0) -> 1 | L27: =IF(H27="0 (checked)",2,IF(H27="Unverified",1,IF(H27="1 (checked)",0.5,0))) -> 1 | M27: =I27+J27+K27+L27 -> 8 | N27: =IF(C27<25,"Nano (<$25M)",IF(C27<100,"$25-100M",IF(C27<250,"$100-250M","$250-500M"))) -> $100-250M
A28: NEN | B28: New England Realty Associates | C28: 173.41 | D28: Apartment owner | E28: Rents shaped by local rent rules and new-supply permits in specific metros | F28: Local rent boards (e.g., NYC Rent Guidelines Board); multifamily permits; eviction filings; property-tax assessments | G28: Boston-area apartments - rent policy | H28: Unverified | I28: 3 | J28: 3 | K28: =IF(C28>=50,1,0) -> 1 | L28: =IF(H28="0 (checked)",2,IF(H28="Unverified",1,IF(H28="1 (checked)",0.5,0))) -> 1 | M28: =I28+J28+K28+L28 -> 8 | N28: =IF(C28<25,"Nano (<$25M)",IF(C28<100,"$25-100M",IF(C28<250,"$100-250M","$250-500M"))) -> $100-250M
A29: ESOA | B29: Energy Services of America | C29: 171.85 | D29: Public-works contractor | E29: Revenue won through state DOT, municipal and utility contract lettings | F29: State DOT bid lettings & awards; municipal procurement portals; utility capex filings | G29: Utility & broadband contractor - WV/Appalachia | H29: Unverified | I29: 3 | J29: 3 | K29: =IF(C29>=50,1,0) -> 1 | L29: =IF(H29="0 (checked)",2,IF(H29="Unverified",1,IF(H29="1 (checked)",0.5,0))) -> 1 | M29: =I29+J29+K29+L29 -> 8 | N29: =IF(C29<25,"Nano (<$25M)",IF(C29<100,"$25-100M",IF(C29<250,"$100-250M","$250-500M"))) -> $100-250M
A30: ELME | B30: Elme Communities | C30: 155.52 | D30: Apartment owner | E30: Rents shaped by local rent rules and new-supply permits in specific metros | F30: Local rent boards (e.g., NYC Rent Guidelines Board); multifamily permits; eviction filings; property-tax assessments | G30: DC-area apartments | H30: Unverified | I30: 3 | J30: 3 | K30: =IF(C30>=50,1,0) -> 1 | L30: =IF(H30="0 (checked)",2,IF(H30="Unverified",1,IF(H30="1 (checked)",0.5,0))) -> 1 | M30: =I30+J30+K30+L30 -> 8 | N30: =IF(C30<25,"Nano (<$25M)",IF(C30<100,"$25-100M",IF(C30<250,"$100-250M","$250-500M"))) -> $100-250M
A31: OZ | B31: Belpointe PREP | C31: 152.09 | D31: Land / entitlement developer | E31: Value unlocked by entitlements, zoning, plats and permits on specific parcels | F31: Planning commission & council agendas; plat approvals; Census BPS; county deed and assessor records | G31: Opportunity-zone developments; local approvals | H31: Unverified | I31: 3 | J31: 3 | K31: =IF(C31>=50,1,0) -> 1 | L31: =IF(H31="0 (checked)",2,IF(H31="Unverified",1,IF(H31="1 (checked)",0.5,0))) -> 1 | M31: =I31+J31+K31+L31 -> 8 | N31: =IF(C31<25,"Nano (<$25M)",IF(C31<100,"$25-100M",IF(C31<250,"$100-250M","$250-500M"))) -> $100-250M
A32: CLPR | B32: Clipper Realty | C32: 133.8 | D32: Apartment owner | E32: Rents shaped by local rent rules and new-supply permits in specific metros | F32: Local rent boards (e.g., NYC Rent Guidelines Board); multifamily permits; eviction filings; property-tax assessments | G32: NYC rent-stabilized units - Rent Guidelines Board votes | H32: Unverified | I32: 3 | J32: 3 | K32: =IF(C32>=50,1,0) -> 1 | L32: =IF(H32="0 (checked)",2,IF(H32="Unverified",1,IF(H32="1 (checked)",0.5,0))) -> 1 | M32: =I32+J32+K32+L32 -> 8 | N32: =IF(C32<25,"Nano (<$25M)",IF(C32<100,"$25-100M",IF(C32<250,"$100-250M","$250-500M"))) -> $100-250M
A33: SMID | B33: Smith-Midland | C33: 118.82 | D33: Public-works contractor | E33: Revenue won through state DOT, municipal and utility contract lettings | F33: State DOT bid lettings & awards; municipal procurement portals; utility capex filings | G33: State DOT precast/barrier demand | H33: Unverified | I33: 3 | J33: 3 | K33: =IF(C33>=50,1,0) -> 1 | L33: =IF(H33="0 (checked)",2,IF(H33="Unverified",1,IF(H33="1 (checked)",0.5,0))) -> 1 | M33: =I33+J33+K33+L33 -> 8 | N33: =IF(C33<25,"Nano (<$25M)",IF(C33<100,"$25-100M",IF(C33<250,"$100-250M","$250-500M"))) -> $100-250M
A34: BHM | B34: Bluerock Homes Trust | C34: 107.56 | D34: Apartment owner | E34: Rents shaped by local rent rules and new-supply permits in specific metros | F34: Local rent boards (e.g., NYC Rent Guidelines Board); multifamily permits; eviction filings; property-tax assessments | H34: Unverified | I34: 3 | J34: 3 | K34: =IF(C34>=50,1,0) -> 1 | L34: =IF(H34="0 (checked)",2,IF(H34="Unverified",1,IF(H34="1 (checked)",0.5,0))) -> 1 | M34: =I34+J34+K34+L34 -> 8 | N34: =IF(C34<25,"Nano (<$25M)",IF(C34<100,"$25-100M",IF(C34<250,"$100-250M","$250-500M"))) -> $100-250M
A35: STHO | B35: Star Holdings | C35: 102.03 | D35: Land / entitlement developer | E35: Value unlocked by entitlements, zoning, plats and permits on specific parcels | F35: Planning commission & council agendas; plat approvals; Census BPS; county deed and assessor records | G35: Asbury Park, NJ waterfront redevelopment | H35: Unverified | I35: 3 | J35: 3 | K35: =IF(C35>=50,1,0) -> 1 | L35: =IF(H35="0 (checked)",2,IF(H35="Unverified",1,IF(H35="1 (checked)",0.5,0))) -> 1 | M35: =I35+J35+K35+L35 -> 8 | N35: =IF(C35<25,"Nano (<$25M)",IF(C35<100,"$25-100M",IF(C35<250,"$100-250M","$250-500M"))) -> $100-250M
A36: SHIM | B36: Shimmick | C36: 99.62 | D36: Public-works contractor | E36: Revenue won through state DOT, municipal and utility contract lettings | F36: State DOT bid lettings & awards; municipal procurement portals; utility capex filings | G36: Water & public infrastructure | H36: Unverified | I36: 3 | J36: 3 | K36: =IF(C36>=50,1,0) -> 1 | L36: =IF(H36="0 (checked)",2,IF(H36="Unverified",1,IF(H36="1 (checked)",0.5,0))) -> 1 | M36: =I36+J36+K36+L36 -> 8 | N36: =IF(C36<25,"Nano (<$25M)",IF(C36<100,"$25-100M",IF(C36<250,"$100-250M","$250-500M"))) -> $25-100M
A37: SRG | B37: Seritage Growth Properties | C37: 88.43 | D37: Land / entitlement developer | E37: Value unlocked by entitlements, zoning, plats and permits on specific parcels | F37: Planning commission & council agendas; plat approvals; Census BPS; county deed and assessor records | G37: Liquidating former Sears sites - local entitlements drive sale values | H37: Unverified | I37: 3 | J37: 3 | K37: =IF(C37>=50,1,0) -> 1 | L37: =IF(H37="0 (checked)",2,IF(H37="Unverified",1,IF(H37="1 (checked)",0.5,0))) -> 1 | M37: =I37+J37+K37+L37 -> 8 | N37: =IF(C37<25,"Nano (<$25M)",IF(C37<100,"$25-100M",IF(C37<250,"$100-250M","$250-500M"))) -> $25-100M
A38: INTG | B38: InterGroup | C38: 68.57 | D38: Hotel owner | E38: Local hotel demand, convention calendars, city policy | F38: City hotel/occupancy-tax reports; convention-center calendars; local permits | G38: Hilton SF Financial District - SF hotel tax, conventions | H38: 0 (checked) | I38: 2 | J38: 3 | K38: =IF(C38>=50,1,0) -> 1 | L38: =IF(H38="0 (checked)",2,IF(H38="Unverified",1,IF(H38="1 (checked)",0.5,0))) -> 2 | M38: =I38+J38+K38+L38 -> 8 | N38: =IF(C38<25,"Nano (<$25M)",IF(C38<100,"$25-100M",IF(C38<250,"$100-250M","$250-500M"))) -> $25-100M
A39: BLNK | B39: Blink Charging | C39: 61.38 | D39: Public-works contractor | E39: Revenue won through state DOT, municipal and utility contract lettings | F39: State DOT bid lettings & awards; municipal procurement portals; utility capex filings | G39: Municipal EV charging contracts | H39: Unverified | I39: 3 | J39: 3 | K39: =IF(C39>=50,1,0) -> 1 | L39: =IF(H39="0 (checked)",2,IF(H39="Unverified",1,IF(H39="1 (checked)",0.5,0))) -> 1 | M39: =I39+J39+K39+L39 -> 8 | N39: =IF(C39<25,"Nano (<$25M)",IF(C39<100,"$25-100M",IF(C39<250,"$100-250M","$250-500M"))) -> $25-100M
A40: FLL | B40: Full House Resorts | C40: 50.94 | D40: Regional gaming / racing | E40: State gaming & racing commissions license and tax; local approvals for expansions | F40: Monthly state gaming-revenue reports by property; racing commission minutes; city development agendas | G40: Illinois & Colorado gaming boards - monthly property revenue | H40: Unverified | I40: 3 | J40: 3 | K40: =IF(C40>=50,1,0) -> 1 | L40: =IF(H40="0 (checked)",2,IF(H40="Unverified",1,IF(H40="1 (checked)",0.5,0))) -> 1 | M40: =I40+J40+K40+L40 -> 8 | N40: =IF(C40<25,"Nano (<$25M)",IF(C40<100,"$25-100M",IF(C40<250,"$100-250M","$250-500M"))) -> $25-100M
A41: GYRO | B41: Gyrodyne | C41: 10.51 | D41: Land / entitlement developer | E41: Value unlocked by entitlements, zoning, plats and permits on specific parcels | F41: Planning commission & council agendas; plat approvals; Census BPS; county deed and assessor records | G41: Liquidating; Smithtown & Cortlandt, NY approvals | H41: 0 (checked) | I41: 3 | J41: 3 | K41: =IF(C41>=50,1,0) -> 0 | L41: =IF(H41="0 (checked)",2,IF(H41="Unverified",1,IF(H41="1 (checked)",0.5,0))) -> 2 | M41: =I41+J41+K41+L41 -> 8 | N41: =IF(C41<25,"Nano (<$25M)",IF(C41<100,"$25-100M",IF(C41<250,"$100-250M","$250-500M"))) -> Nano (<$25M)
A42: AXR | B42: AMREP Corp | C42: 108.14 | D42: Land / entitlement developer | E42: Value unlocked by entitlements, zoning, plats and permits on specific parcels | F42: Planning commission & council agendas; plat approvals; Census BPS; county deed and assessor records | G42: Rio Rancho, NM plats and permits; 1 analyst (Freedom Broker) | H42: 1 (checked) | I42: 3 | J42: 3 | K42: =IF(C42>=50,1,0) -> 1 | L42: =IF(H42="0 (checked)",2,IF(H42="Unverified",1,IF(H42="1 (checked)",0.5,0))) -> 0.5 | M42: =I42+J42+K42+L42 -> 7.5 | N42: =IF(C42<25,"Nano (<$25M)",IF(C42<100,"$25-100M",IF(C42<250,"$100-250M","$250-500M"))) -> $100-250M
A43: WTBA | B43: West Bancorporation | C43: 497.68 | D43: Community bank | E43: Loan growth, deposits and credit tied to one local economy and its real estate | F43: FFIEC call reports (quarterly, bank-level); FDIC Summary of Deposits (county share); HMDA mortgage data; county permits & deed records | H43: Unverified | I43: 2 | J43: 3 | K43: =IF(C43>=50,1,0) -> 1 | L43: =IF(H43="0 (checked)",2,IF(H43="Unverified",1,IF(H43="1 (checked)",0.5,0))) -> 1 | M43: =I43+J43+K43+L43 -> 7 | N43: =IF(C43<25,"Nano (<$25M)",IF(C43<100,"$25-100M",IF(C43<250,"$100-250M","$250-500M"))) -> $250-500M
A44: PDLB | B44: Ponce Financial Group | C44: 494.16 | D44: Community bank | E44: Loan growth, deposits and credit tied to one local economy and its real estate | F44: FFIEC call reports (quarterly, bank-level); FDIC Summary of Deposits (county share); HMDA mortgage data; county permits & deed records | H44: Unverified | I44: 2 | J44: 3 | K44: =IF(C44>=50,1,0) -> 1 | L44: =IF(H44="0 (checked)",2,IF(H44="Unverified",1,IF(H44="1 (checked)",0.5,0))) -> 1 | M44: =I44+J44+K44+L44 -> 7 | N44: =IF(C44<25,"Nano (<$25M)",IF(C44<100,"$25-100M",IF(C44<250,"$100-250M","$250-500M"))) -> $250-500M
A45: FMAO | B45: Farmers & Merchants Bancorp | C45: 481.88 | D45: Community bank | E45: Loan growth, deposits and credit tied to one local economy and its real estate | F45: FFIEC call reports (quarterly, bank-level); FDIC Summary of Deposits (county share); HMDA mortgage data; county permits & deed records | H45: Unverified | I45: 2 | J45: 3 | K45: =IF(C45>=50,1,0) -> 1 | L45: =IF(H45="0 (checked)",2,IF(H45="Unverified",1,IF(H45="1 (checked)",0.5,0))) -> 1 | M45: =I45+J45+K45+L45 -> 7 | N45: =IF(C45<25,"Nano (<$25M)",IF(C45<100,"$25-100M",IF(C45<250,"$100-250M","$250-500M"))) -> $250-500M
A46: CZNC | B46: Citizens & Northern | C46: 465.05 | D46: Community bank | E46: Loan growth, deposits and credit tied to one local economy and its real estate | F46: FFIEC call reports (quarterly, bank-level); FDIC Summary of Deposits (county share); HMDA mortgage data; county permits & deed records | H46: Unverified | I46: 2 | J46: 3 | K46: =IF(C46>=50,1,0) -> 1 | L46: =IF(H46="0 (checked)",2,IF(H46="Unverified",1,IF(H46="1 (checked)",0.5,0))) -> 1 | M46: =I46+J46+K46+L46 -> 7 | N46: =IF(C46<25,"Nano (<$25M)",IF(C46<100,"$25-100M",IF(C46<250,"$100-250M","$250-500M"))) -> $250-500M
A47: CBK | B47: Commercial Bancgroup | C47: 464.47 | D47: Community bank | E47: Loan growth, deposits and credit tied to one local economy and its real estate | F47: FFIEC call reports (quarterly, bank-level); FDIC Summary of Deposits (county share); HMDA mortgage data; county permits & deed records | H47: Unverified | I47: 2 | J47: 3 | K47: =IF(C47>=50,1,0) -> 1 | L47: =IF(H47="0 (checked)",2,IF(H47="Unverified",1,IF(H47="1 (checked)",0.5,0))) -> 1 | M47: =I47+J47+K47+L47 -> 7 | N47: =IF(C47<25,"Nano (<$25M)",IF(C47<100,"$25-100M",IF(C47<250,"$100-250M","$250-500M"))) -> $250-500M
A48: CBAN | B48: Colony Bankcorp | C48: 455.4 | D48: Community bank | E48: Loan growth, deposits and credit tied to one local economy and its real estate | F48: FFIEC call reports (quarterly, bank-level); FDIC Summary of Deposits (county share); HMDA mortgage data; county permits & deed records | H48: Unverified | I48: 2 | J48: 3 | K48: =IF(C48>=50,1,0) -> 1 | L48: =IF(H48="0 (checked)",2,IF(H48="Unverified",1,IF(H48="1 (checked)",0.5,0))) -> 1 | M48: =I48+J48+K48+L48 -> 7 | N48: =IF(C48<25,"Nano (<$25M)",IF(C48<100,"$25-100M",IF(C48<250,"$100-250M","$250-500M"))) -> $250-500M
A49: CWCO | B49: Consolidated Water | C49: 452.2 | D49: Regulated utility | E49: State commission sets rates; customer additions come from local development approvals | F49: State PUC/SCC rate dockets; county subdivision approvals; Census Building Permits Survey | G49: Cayman/Bahamas government water licenses - non-US operations | H49: Unverified | I49: 3 | J49: 2 | K49: =IF(C49>=50,1,0) -> 1 | L49: =IF(H49="0 (checked)",2,IF(H49="Unverified",1,IF(H49="1 (checked)",0.5,0))) -> 1 | M49: =I49+J49+K49+L49 -> 7 | N49: =IF(C49<25,"Nano (<$25M)",IF(C49<100,"$25-100M",IF(C49<250,"$100-250M","$250-500M"))) -> $250-500M
A50: RBB | B50: RBB Bancorp | C50: 451.32 | D50: Community bank | E50: Loan growth, deposits and credit tied to one local economy and its real estate | F50: FFIEC call reports (quarterly, bank-level); FDIC Summary of Deposits (county share); HMDA mortgage data; county permits & deed records | H50: Unverified | I50: 2 | J50: 3 | K50: =IF(C50>=50,1,0) -> 1 | L50: =IF(H50="0 (checked)",2,IF(H50="Unverified",1,IF(H50="1 (checked)",0.5,0))) -> 1 | M50: =I50+J50+K50+L50 -> 7 | N50: =IF(C50<25,"Nano (<$25M)",IF(C50<100,"$25-100M",IF(C50<250,"$100-250M","$250-500M"))) -> $250-500M
A51: FRBA | B51: First Bank | C51: 444.33 | D51: Community bank | E51: Loan growth, deposits and credit tied to one local economy and its real estate | F51: FFIEC call reports (quarterly, bank-level); FDIC Summary of Deposits (county share); HMDA mortgage data; county permits & deed records | H51: Unverified | I51: 2 | J51: 3 | K51: =IF(C51>=50,1,0) -> 1 | L51: =IF(H51="0 (checked)",2,IF(H51="Unverified",1,IF(H51="1 (checked)",0.5,0))) -> 1 | M51: =I51+J51+K51+L51 -> 7 | N51: =IF(C51<25,"Nano (<$25M)",IF(C51<100,"$25-100M",IF(C51<250,"$100-250M","$250-500M"))) -> $250-500M
A52: GNE | B52: Genie Energy | C52: 443.35 | D52: Regulated utility | E52: State commission sets rates; customer additions come from local development approvals | F52: State PUC/SCC rate dockets; county subdivision approvals; Census Building Permits Survey | G52: Retail energy - state PUC retail-choice rules | H52: Unverified | I52: 3 | J52: 2 | K52: =IF(C52>=50,1,0) -> 1 | L52: =IF(H52="0 (checked)",2,IF(H52="Unverified",1,IF(H52="1 (checked)",0.5,0))) -> 1 | M52: =I52+J52+K52+L52 -> 7 | N52: =IF(C52<25,"Nano (<$25M)",IF(C52<100,"$25-100M",IF(C52<250,"$100-250M","$250-500M"))) -> $250-500M
A53: BMRC | B53: Bank of Marin Bancorp | C53: 443.18 | D53: Community bank | E53: Loan growth, deposits and credit tied to one local economy and its real estate | F53: FFIEC call reports (quarterly, bank-level); FDIC Summary of Deposits (county share); HMDA mortgage data; county permits & deed records | H53: Unverified | I53: 2 | J53: 3 | K53: =IF(C53>=50,1,0) -> 1 | L53: =IF(H53="0 (checked)",2,IF(H53="Unverified",1,IF(H53="1 (checked)",0.5,0))) -> 1 | M53: =I53+J53+K53+L53 -> 7 | N53: =IF(C53<25,"Nano (<$25M)",IF(C53<100,"$25-100M",IF(C53<250,"$100-250M","$250-500M"))) -> $250-500M
A54: PBFS | B54: Pioneer Bancorp | C54: 437.63 | D54: Community bank | E54: Loan growth, deposits and credit tied to one local economy and its real estate | F54: FFIEC call reports (quarterly, bank-level); FDIC Summary of Deposits (county share); HMDA mortgage data; county permits & deed records | H54: Unverified | I54: 2 | J54: 3 | K54: =IF(C54>=50,1,0) -> 1 | L54: =IF(H54="0 (checked)",2,IF(H54="Unverified",1,IF(H54="1 (checked)",0.5,0))) -> 1 | M54: =I54+J54+K54+L54 -> 7 | N54: =IF(C54<25,"Nano (<$25M)",IF(C54<100,"$25-100M",IF(C54<250,"$100-250M","$250-500M"))) -> $250-500M
A55: PLBC | B55: Plumas Bancorp | C55: 434.8 | D55: Community bank | E55: Loan growth, deposits and credit tied to one local economy and its real estate | F55: FFIEC call reports (quarterly, bank-level); FDIC Summary of Deposits (county share); HMDA mortgage data; county permits & deed records | H55: Unverified | I55: 2 | J55: 3 | K55: =IF(C55>=50,1,0) -> 1 | L55: =IF(H55="0 (checked)",2,IF(H55="Unverified",1,IF(H55="1 (checked)",0.5,0))) -> 1 | M55: =I55+J55+K55+L55 -> 7 | N55: =IF(C55<25,"Nano (<$25M)",IF(C55<100,"$25-100M",IF(C55<250,"$100-250M","$250-500M"))) -> $250-500M
A56: ATNI | B56: ATN International | C56: 433.73 | D56: Broadband / local media infrastructure | E56: Municipal franchises, state BEAD broadband grants, local permits | F56: State broadband office BEAD award lists; FCC broadband maps; municipal franchise agendas | G56: Rural broadband grants; US Virgin Islands | H56: Unverified | I56: 2 | J56: 3 | K56: =IF(C56>=50,1,0) -> 1 | L56: =IF(H56="0 (checked)",2,IF(H56="Unverified",1,IF(H56="1 (checked)",0.5,0))) -> 1 | M56: =I56+J56+K56+L56 -> 7 | N56: =IF(C56<25,"Nano (<$25M)",IF(C56<100,"$25-100M",IF(C56<250,"$100-250M","$250-500M"))) -> $250-500M
A57: USCB | B57: USCB Financial Holdings | C57: 424.73 | D57: Community bank | E57: Loan growth, deposits and credit tied to one local economy and its real estate | F57: FFIEC call reports (quarterly, bank-level); FDIC Summary of Deposits (county share); HMDA mortgage data; county permits & deed records | H57: Unverified | I57: 2 | J57: 3 | K57: =IF(C57>=50,1,0) -> 1 | L57: =IF(H57="0 (checked)",2,IF(H57="Unverified",1,IF(H57="1 (checked)",0.5,0))) -> 1 | M57: =I57+J57+K57+L57 -> 7 | N57: =IF(C57<25,"Nano (<$25M)",IF(C57<100,"$25-100M",IF(C57<250,"$100-250M","$250-500M"))) -> $250-500M
A58: ISTR | B58: Investar Holding | C58: 422.54 | D58: Community bank | E58: Loan growth, deposits and credit tied to one local economy and its real estate | F58: FFIEC call reports (quarterly, bank-level); FDIC Summary of Deposits (county share); HMDA mortgage data; county permits & deed records | H58: Unverified | I58: 2 | J58: 3 | K58: =IF(C58>=50,1,0) -> 1 | L58: =IF(H58="0 (checked)",2,IF(H58="Unverified",1,IF(H58="1 (checked)",0.5,0))) -> 1 | M58: =I58+J58+K58+L58 -> 7 | N58: =IF(C58<25,"Nano (<$25M)",IF(C58<100,"$25-100M",IF(C58<250,"$100-250M","$250-500M"))) -> $250-500M
A59: CHMG | B59: Chemung Financial | C59: 408.91 | D59: Community bank | E59: Loan growth, deposits and credit tied to one local economy and its real estate | F59: FFIEC call reports (quarterly, bank-level); FDIC Summary of Deposits (county share); HMDA mortgage data; county permits & deed records | H59: Unverified | I59: 2 | J59: 3 | K59: =IF(C59>=50,1,0) -> 1 | L59: =IF(H59="0 (checked)",2,IF(H59="Unverified",1,IF(H59="1 (checked)",0.5,0))) -> 1 | M59: =I59+J59+K59+L59 -> 7 | N59: =IF(C59<25,"Nano (<$25M)",IF(C59<100,"$25-100M",IF(C59<250,"$100-250M","$250-500M"))) -> $250-500M
A60: OPAL | B60: OPAL Fuels | C60: 407.18 | D60: Energy project developer | E60: County zoning/siting votes and state incentive programs decide whether projects get built | F60: County zoning agendas (siting moratoriums); state program dockets (community solar, LCFS); interconnection queues | G60: Landfill-gas RNG; state LCFS programs and landfill host agreements | H60: Unverified | I60: 3 | J60: 2 | K60: =IF(C60>=50,1,0) -> 1 | L60: =IF(H60="0 (checked)",2,IF(H60="Unverified",1,IF(H60="1 (checked)",0.5,0))) -> 1 | M60: =I60+J60+K60+L60 -> 7 | N60: =IF(C60<25,"Nano (<$25M)",IF(C60<100,"$25-100M",IF(C60<250,"$100-250M","$250-500M"))) -> $250-500M
A61: PKBK | B61: Parke Bancorp | C61: 406.83 | D61: Community bank | E61: Loan growth, deposits and credit tied to one local economy and its real estate | F61: FFIEC call reports (quarterly, bank-level); FDIC Summary of Deposits (county share); HMDA mortgage data; county permits & deed records | H61: Unverified | I61: 2 | J61: 3 | K61: =IF(C61>=50,1,0) -> 1 | L61: =IF(H61="0 (checked)",2,IF(H61="Unverified",1,IF(H61="1 (checked)",0.5,0))) -> 1 | M61: =I61+J61+K61+L61 -> 7 | N61: =IF(C61<25,"Nano (<$25M)",IF(C61<100,"$25-100M",IF(C61<250,"$100-250M","$250-500M"))) -> $250-500M
A62: MVBF | B62: MVB Financial | C62: 406.14 | D62: Community bank | E62: Loan growth, deposits and credit tied to one local economy and its real estate | F62: FFIEC call reports (quarterly, bank-level); FDIC Summary of Deposits (county share); HMDA mortgage data; county permits & deed records | H62: Unverified | I62: 2 | J62: 3 | K62: =IF(C62>=50,1,0) -> 1 | L62: =IF(H62="0 (checked)",2,IF(H62="Unverified",1,IF(H62="1 (checked)",0.5,0))) -> 1 | M62: =I62+J62+K62+L62 -> 7 | N62: =IF(C62<25,"Nano (<$25M)",IF(C62<100,"$25-100M",IF(C62<250,"$100-250M","$250-500M"))) -> $250-500M
A63: AVBC | B63: Avidia Bancorp | C63: 402.04 | D63: Community bank | E63: Loan growth, deposits and credit tied to one local economy and its real estate | F63: FFIEC call reports (quarterly, bank-level); FDIC Summary of Deposits (county share); HMDA mortgage data; county permits & deed records | H63: Unverified | I63: 2 | J63: 3 | K63: =IF(C63>=50,1,0) -> 1 | L63: =IF(H63="0 (checked)",2,IF(H63="Unverified",1,IF(H63="1 (checked)",0.5,0))) -> 1 | M63: =I63+J63+K63+L63 -> 7 | N63: =IF(C63<25,"Nano (<$25M)",IF(C63<100,"$25-100M",IF(C63<250,"$100-250M","$250-500M"))) -> $250-500M
A64: URG | B64: Ur-Energy | C64: 401.54 | D64: Mine developer / producer | E64: State mine, water and air permits plus county approvals gate the project | F64: State environmental agency permit dockets; county commission agendas; state mining reports | G64: Wyoming state permits | H64: Unverified | I64: 3 | J64: 2 | K64: =IF(C64>=50,1,0) -> 1 | L64: =IF(H64="0 (checked)",2,IF(H64="Unverified",1,IF(H64="1 (checked)",0.5,0))) -> 1 | M64: =I64+J64+K64+L64 -> 7 | N64: =IF(C64<25,"Nano (<$25M)",IF(C64<100,"$25-100M",IF(C64<250,"$100-250M","$250-500M"))) -> $250-500M
A65: OPTU | B65: Optimum Communications | C65: 400.41 | D65: Broadband / local media infrastructure | E65: Municipal franchises, state BEAD broadband grants, local permits | F65: State broadband office BEAD award lists; FCC broadband maps; municipal franchise agendas | G65: Municipal franchises - verify cap/structure | H65: Unverified | I65: 2 | J65: 3 | K65: =IF(C65>=50,1,0) -> 1 | L65: =IF(H65="0 (checked)",2,IF(H65="Unverified",1,IF(H65="1 (checked)",0.5,0))) -> 1 | M65: =I65+J65+K65+L65 -> 7 | N65: =IF(C65<25,"Nano (<$25M)",IF(C65<100,"$25-100M",IF(C65<250,"$100-250M","$250-500M"))) -> $250-500M
A66: CZFS | B66: Citizens Financial Services | C66: 399.8 | D66: Community bank | E66: Loan growth, deposits and credit tied to one local economy and its real estate | F66: FFIEC call reports (quarterly, bank-level); FDIC Summary of Deposits (county share); HMDA mortgage data; county permits & deed records | H66: Unverified | I66: 2 | J66: 3 | K66: =IF(C66>=50,1,0) -> 1 | L66: =IF(H66="0 (checked)",2,IF(H66="Unverified",1,IF(H66="1 (checked)",0.5,0))) -> 1 | M66: =I66+J66+K66+L66 -> 7 | N66: =IF(C66<25,"Nano (<$25M)",IF(C66<100,"$25-100M",IF(C66<250,"$100-250M","$250-500M"))) -> $250-500M
A67: BOC | B67: Boston Omaha | C67: 398.27 | D67: Broadband / local media infrastructure | E67: Municipal franchises, state BEAD broadband grants, local permits | F67: State broadband office BEAD award lists; FCC broadband maps; municipal franchise agendas | G67: Billboard permits & municipal broadband | H67: Unverified | I67: 2 | J67: 3 | K67: =IF(C67>=50,1,0) -> 1 | L67: =IF(H67="0 (checked)",2,IF(H67="Unverified",1,IF(H67="1 (checked)",0.5,0))) -> 1 | M67: =I67+J67+K67+L67 -> 7 | N67: =IF(C67<25,"Nano (<$25M)",IF(C67<100,"$25-100M",IF(C67<250,"$100-250M","$250-500M"))) -> $250-500M
A68: FRST | B68: Primis Financial | C68: 398.23 | D68: Community bank | E68: Loan growth, deposits and credit tied to one local economy and its real estate | F68: FFIEC call reports (quarterly, bank-level); FDIC Summary of Deposits (county share); HMDA mortgage data; county permits & deed records | H68: Unverified | I68: 2 | J68: 3 | K68: =IF(C68>=50,1,0) -> 1 | L68: =IF(H68="0 (checked)",2,IF(H68="Unverified",1,IF(H68="1 (checked)",0.5,0))) -> 1 | M68: =I68+J68+K68+L68 -> 7 | N68: =IF(C68<25,"Nano (<$25M)",IF(C68<100,"$25-100M",IF(C68<250,"$100-250M","$250-500M"))) -> $250-500M
A69: FCBM | B69: First Carolina Financial Services | C69: 396.75 | D69: Community bank | E69: Loan growth, deposits and credit tied to one local economy and its real estate | F69: FFIEC call reports (quarterly, bank-level); FDIC Summary of Deposits (county share); HMDA mortgage data; county permits & deed records | H69: Unverified | I69: 2 | J69: 3 | K69: =IF(C69>=50,1,0) -> 1 | L69: =IF(H69="0 (checked)",2,IF(H69="Unverified",1,IF(H69="1 (checked)",0.5,0))) -> 1 | M69: =I69+J69+K69+L69 -> 7 | N69: =IF(C69<25,"Nano (<$25M)",IF(C69<100,"$25-100M",IF(C69<250,"$100-250M","$250-500M"))) -> $250-500M
A70: FNLC | B70: The First Bancorp | C70: 395.33 | D70: Community bank | E70: Loan growth, deposits and credit tied to one local economy and its real estate | F70: FFIEC call reports (quarterly, bank-level); FDIC Summary of Deposits (county share); HMDA mortgage data; county permits & deed records | H70: Unverified | I70: 2 | J70: 3 | K70: =IF(C70>=50,1,0) -> 1 | L70: =IF(H70="0 (checked)",2,IF(H70="Unverified",1,IF(H70="1 (checked)",0.5,0))) -> 1 | M70: =I70+J70+K70+L70 -> 7 | N70: =IF(C70<25,"Nano (<$25M)",IF(C70<100,"$25-100M",IF(C70<250,"$100-250M","$250-500M"))) -> $250-500M
A71: PCB | B71: PCB Bancorp | C71: 389.03 | D71: Community bank | E71: Loan growth, deposits and credit tied to one local economy and its real estate | F71: FFIEC call reports (quarterly, bank-level); FDIC Summary of Deposits (county share); HMDA mortgage data; county permits & deed records | H71: Unverified | I71: 2 | J71: 3 | K71: =IF(C71>=50,1,0) -> 1 | L71: =IF(H71="0 (checked)",2,IF(H71="Unverified",1,IF(H71="1 (checked)",0.5,0))) -> 1 | M71: =I71+J71+K71+L71 -> 7 | N71: =IF(C71<25,"Nano (<$25M)",IF(C71<100,"$25-100M",IF(C71<250,"$100-250M","$250-500M"))) -> $250-500M
A72: FRPH | B72: FRP Holdings | C72: 388 | D72: Property owner (commercial) | E72: Asset values and leasing in a handful of metros; zoning and property-tax decisions | F72: County assessor/recorder data; local building permits; zoning/rezoning agendas | G72: DC/Maryland real estate + FL/GA/VA mining royalties (DOT lettings) | H72: 0 (checked) | I72: 2 | J72: 2 | K72: =IF(C72>=50,1,0) -> 1 | L72: =IF(H72="0 (checked)",2,IF(H72="Unverified",1,IF(H72="1 (checked)",0.5,0))) -> 2 | M72: =I72+J72+K72+L72 -> 7 | N72: =IF(C72<25,"Nano (<$25M)",IF(C72<100,"$25-100M",IF(C72<250,"$100-250M","$250-500M"))) -> $250-500M
A73: WSBF | B73: Waterstone Financial | C73: 383.95 | D73: Community bank | E73: Loan growth, deposits and credit tied to one local economy and its real estate | F73: FFIEC call reports (quarterly, bank-level); FDIC Summary of Deposits (county share); HMDA mortgage data; county permits & deed records | H73: Unverified | I73: 2 | J73: 3 | K73: =IF(C73>=50,1,0) -> 1 | L73: =IF(H73="0 (checked)",2,IF(H73="Unverified",1,IF(H73="1 (checked)",0.5,0))) -> 1 | M73: =I73+J73+K73+L73 -> 7 | N73: =IF(C73<25,"Nano (<$25M)",IF(C73<100,"$25-100M",IF(C73<250,"$100-250M","$250-500M"))) -> $250-500M
A74: NWFL | B74: Norwood Financial | C74: 373.27 | D74: Community bank | E74: Loan growth, deposits and credit tied to one local economy and its real estate | F74: FFIEC call reports (quarterly, bank-level); FDIC Summary of Deposits (county share); HMDA mortgage data; county permits & deed records | H74: Unverified | I74: 2 | J74: 3 | K74: =IF(C74>=50,1,0) -> 1 | L74: =IF(H74="0 (checked)",2,IF(H74="Unverified",1,IF(H74="1 (checked)",0.5,0))) -> 1 | M74: =I74+J74+K74+L74 -> 7 | N74: =IF(C74<25,"Nano (<$25M)",IF(C74<100,"$25-100M",IF(C74<250,"$100-250M","$250-500M"))) -> $250-500M
A75: BRBS | B75: Blue Ridge Bankshares | C75: 364.13 | D75: Community bank | E75: Loan growth, deposits and credit tied to one local economy and its real estate | F75: FFIEC call reports (quarterly, bank-level); FDIC Summary of Deposits (county share); HMDA mortgage data; county permits & deed records | H75: Unverified | I75: 2 | J75: 3 | K75: =IF(C75>=50,1,0) -> 1 | L75: =IF(H75="0 (checked)",2,IF(H75="Unverified",1,IF(H75="1 (checked)",0.5,0))) -> 1 | M75: =I75+J75+K75+L75 -> 7 | N75: =IF(C75<25,"Nano (<$25M)",IF(C75<100,"$25-100M",IF(C75<250,"$100-250M","$250-500M"))) -> $250-500M
A76: TSBK | B76: Timberland Bancorp | C76: 361.96 | D76: Community bank | E76: Loan growth, deposits and credit tied to one local economy and its real estate | F76: FFIEC call reports (quarterly, bank-level); FDIC Summary of Deposits (county share); HMDA mortgage data; county permits & deed records | H76: Unverified | I76: 2 | J76: 3 | K76: =IF(C76>=50,1,0) -> 1 | L76: =IF(H76="0 (checked)",2,IF(H76="Unverified",1,IF(H76="1 (checked)",0.5,0))) -> 1 | M76: =I76+J76+K76+L76 -> 7 | N76: =IF(C76<25,"Nano (<$25M)",IF(C76<100,"$25-100M",IF(C76<250,"$100-250M","$250-500M"))) -> $250-500M
A77: NEWT | B77: NewtekOne | C77: 351.53 | D77: Community bank | E77: Loan growth, deposits and credit tied to one local economy and its real estate | F77: FFIEC call reports (quarterly, bank-level); FDIC Summary of Deposits (county share); HMDA mortgage data; county permits & deed records | G77: National fintech lender - weaker local link | H77: Unverified | I77: 2 | J77: 3 | K77: =IF(C77>=50,1,0) -> 1 | L77: =IF(H77="0 (checked)",2,IF(H77="Unverified",1,IF(H77="1 (checked)",0.5,0))) -> 1 | M77: =I77+J77+K77+L77 -> 7 | N77: =IF(C77<25,"Nano (<$25M)",IF(C77<100,"$25-100M",IF(C77<250,"$100-250M","$250-500M"))) -> $250-500M
A78: AVBH | B78: Avidbank Holdings | C78: 347.08 | D78: Community bank | E78: Loan growth, deposits and credit tied to one local economy and its real estate | F78: FFIEC call reports (quarterly, bank-level); FDIC Summary of Deposits (county share); HMDA mortgage data; county permits & deed records | H78: Unverified | I78: 2 | J78: 3 | K78: =IF(C78>=50,1,0) -> 1 | L78: =IF(H78="0 (checked)",2,IF(H78="Unverified",1,IF(H78="1 (checked)",0.5,0))) -> 1 | M78: =I78+J78+K78+L78 -> 7 | N78: =IF(C78<25,"Nano (<$25M)",IF(C78<100,"$25-100M",IF(C78<250,"$100-250M","$250-500M"))) -> $250-500M
A79: IDR | B79: Idaho Strategic Resources | C79: 345.17 | D79: Mine developer / producer | E79: State mine, water and air permits plus county approvals gate the project | F79: State environmental agency permit dockets; county commission agendas; state mining reports | G79: Idaho | H79: Unverified | I79: 3 | J79: 2 | K79: =IF(C79>=50,1,0) -> 1 | L79: =IF(H79="0 (checked)",2,IF(H79="Unverified",1,IF(H79="1 (checked)",0.5,0))) -> 1 | M79: =I79+J79+K79+L79 -> 7 | N79: =IF(C79<25,"Nano (<$25M)",IF(C79<100,"$25-100M",IF(C79<250,"$100-250M","$250-500M"))) -> $250-500M
A80: REI | B80: Ring Energy | C80: 342.61 | D80: Oil & gas producer / royalty | E80: Production, permits and spacing on specific acreage set by state regulators | F80: State oil & gas commission well permits & monthly production (Texas RRC, NM OCD, Oklahoma OCC, Louisiana SONRIS, etc.) | H80: Unverified | I80: 2 | J80: 3 | K80: =IF(C80>=50,1,0) -> 1 | L80: =IF(H80="0 (checked)",2,IF(H80="Unverified",1,IF(H80="1 (checked)",0.5,0))) -> 1 | M80: =I80+J80+K80+L80 -> 7 | N80: =IF(C80<25,"Nano (<$25M)",IF(C80<100,"$25-100M",IF(C80<250,"$100-250M","$250-500M"))) -> $250-500M
A81: NECB | B81: Northeast Community Bancorp | C81: 332.66 | D81: Community bank | E81: Loan growth, deposits and credit tied to one local economy and its real estate | F81: FFIEC call reports (quarterly, bank-level); FDIC Summary of Deposits (county share); HMDA mortgage data; county permits & deed records | H81: Unverified | I81: 2 | J81: 3 | K81: =IF(C81>=50,1,0) -> 1 | L81: =IF(H81="0 (checked)",2,IF(H81="Unverified",1,IF(H81="1 (checked)",0.5,0))) -> 1 | M81: =I81+J81+K81+L81 -> 7 | N81: =IF(C81<25,"Nano (<$25M)",IF(C81<100,"$25-100M",IF(C81<250,"$100-250M","$250-500M"))) -> $250-500M
A82: FVCB | B82: FVCBankcorp | C82: 332.37 | D82: Community bank | E82: Loan growth, deposits and credit tied to one local economy and its real estate | F82: FFIEC call reports (quarterly, bank-level); FDIC Summary of Deposits (county share); HMDA mortgage data; county permits & deed records | H82: Unverified | I82: 2 | J82: 3 | K82: =IF(C82>=50,1,0) -> 1 | L82: =IF(H82="0 (checked)",2,IF(H82="Unverified",1,IF(H82="1 (checked)",0.5,0))) -> 1 | M82: =I82+J82+K82+L82 -> 7 | N82: =IF(C82<25,"Nano (<$25M)",IF(C82<100,"$25-100M",IF(C82<250,"$100-250M","$250-500M"))) -> $250-500M
A83: COSO | B83: CoastalSouth Bancshares | C83: 329.58 | D83: Community bank | E83: Loan growth, deposits and credit tied to one local economy and its real estate | F83: FFIEC call reports (quarterly, bank-level); FDIC Summary of Deposits (county share); HMDA mortgage data; county permits & deed records | H83: Unverified | I83: 2 | J83: 3 | K83: =IF(C83>=50,1,0) -> 1 | L83: =IF(H83="0 (checked)",2,IF(H83="Unverified",1,IF(H83="1 (checked)",0.5,0))) -> 1 | M83: =I83+J83+K83+L83 -> 7 | N83: =IF(C83<25,"Nano (<$25M)",IF(C83<100,"$25-100M",IF(C83<250,"$100-250M","$250-500M"))) -> $250-500M
A84: PNRG | B84: PrimeEnergy Resources | C84: 328.23 | D84: Oil & gas producer / royalty | E84: Production, permits and spacing on specific acreage set by state regulators | F84: State oil & gas commission well permits & monthly production (Texas RRC, NM OCD, Oklahoma OCC, Louisiana SONRIS, etc.) | H84: Unverified | I84: 2 | J84: 3 | K84: =IF(C84>=50,1,0) -> 1 | L84: =IF(H84="0 (checked)",2,IF(H84="Unverified",1,IF(H84="1 (checked)",0.5,0))) -> 1 | M84: =I84+J84+K84+L84 -> 7 | N84: =IF(C84<25,"Nano (<$25M)",IF(C84<100,"$25-100M",IF(C84<250,"$100-250M","$250-500M"))) -> $250-500M
A85: BCML | B85: BayCom Corp | C85: 327.89 | D85: Community bank | E85: Loan growth, deposits and credit tied to one local economy and its real estate | F85: FFIEC call reports (quarterly, bank-level); FDIC Summary of Deposits (county share); HMDA mortgage data; county permits & deed records | H85: Unverified | I85: 2 | J85: 3 | K85: =IF(C85>=50,1,0) -> 1 | L85: =IF(H85="0 (checked)",2,IF(H85="Unverified",1,IF(H85="1 (checked)",0.5,0))) -> 1 | M85: =I85+J85+K85+L85 -> 7 | N85: =IF(C85<25,"Nano (<$25M)",IF(C85<100,"$25-100M",IF(C85<250,"$100-250M","$250-500M"))) -> $250-500M
A86: JMSB | B86: John Marshall Bancorp | C86: 325.69 | D86: Community bank | E86: Loan growth, deposits and credit tied to one local economy and its real estate | F86: FFIEC call reports (quarterly, bank-level); FDIC Summary of Deposits (county share); HMDA mortgage data; county permits & deed records | H86: Unverified | I86: 2 | J86: 3 | K86: =IF(C86>=50,1,0) -> 1 | L86: =IF(H86="0 (checked)",2,IF(H86="Unverified",1,IF(H86="1 (checked)",0.5,0))) -> 1 | M86: =I86+J86+K86+L86 -> 7 | N86: =IF(C86<25,"Nano (<$25M)",IF(C86<100,"$25-100M",IF(C86<250,"$100-250M","$250-500M"))) -> $250-500M
A87: FCCO | B87: First Community Corp | C87: 321 | D87: Community bank | E87: Loan growth, deposits and credit tied to one local economy and its real estate | F87: FFIEC call reports (quarterly, bank-level); FDIC Summary of Deposits (county share); HMDA mortgage data; county permits & deed records | H87: Unverified | I87: 2 | J87: 3 | K87: =IF(C87>=50,1,0) -> 1 | L87: =IF(H87="0 (checked)",2,IF(H87="Unverified",1,IF(H87="1 (checked)",0.5,0))) -> 1 | M87: =I87+J87+K87+L87 -> 7 | N87: =IF(C87<25,"Nano (<$25M)",IF(C87<100,"$25-100M",IF(C87<250,"$100-250M","$250-500M"))) -> $250-500M
A88: FDBC | B88: Fidelity D & D Bancorp | C88: 318.95 | D88: Community bank | E88: Loan growth, deposits and credit tied to one local economy and its real estate | F88: FFIEC call reports (quarterly, bank-level); FDIC Summary of Deposits (county share); HMDA mortgage data; county permits & deed records | H88: Unverified | I88: 2 | J88: 3 | K88: =IF(C88>=50,1,0) -> 1 | L88: =IF(H88="0 (checked)",2,IF(H88="Unverified",1,IF(H88="1 (checked)",0.5,0))) -> 1 | M88: =I88+J88+K88+L88 -> 7 | N88: =IF(C88<25,"Nano (<$25M)",IF(C88<100,"$25-100M",IF(C88<250,"$100-250M","$250-500M"))) -> $250-500M
A89: FSBW | B89: FS Bancorp | C89: 318.15 | D89: Community bank | E89: Loan growth, deposits and credit tied to one local economy and its real estate | F89: FFIEC call reports (quarterly, bank-level); FDIC Summary of Deposits (county share); HMDA mortgage data; county permits & deed records | H89: Unverified | I89: 2 | J89: 3 | K89: =IF(C89>=50,1,0) -> 1 | L89: =IF(H89="0 (checked)",2,IF(H89="Unverified",1,IF(H89="1 (checked)",0.5,0))) -> 1 | M89: =I89+J89+K89+L89 -> 7 | N89: =IF(C89<25,"Nano (<$25M)",IF(C89<100,"$25-100M",IF(C89<250,"$100-250M","$250-500M"))) -> $250-500M
A90: FTW | B90: Presidio Production Co | C90: 313.88 | D90: Oil & gas producer / royalty | E90: Production, permits and spacing on specific acreage set by state regulators | F90: State oil & gas commission well permits & monthly production (Texas RRC, NM OCD, Oklahoma OCC, Louisiana SONRIS, etc.) | H90: Unverified | I90: 2 | J90: 3 | K90: =IF(C90>=50,1,0) -> 1 | L90: =IF(H90="0 (checked)",2,IF(H90="Unverified",1,IF(H90="1 (checked)",0.5,0))) -> 1 | M90: =I90+J90+K90+L90 -> 7 | N90: =IF(C90<25,"Nano (<$25M)",IF(C90<100,"$25-100M",IF(C90<250,"$100-250M","$250-500M"))) -> $250-500M
A91: CBNA | B91: Chain Bridge Bancorp | C91: 306.24 | D91: Community bank | E91: Loan growth, deposits and credit tied to one local economy and its real estate | F91: FFIEC call reports (quarterly, bank-level); FDIC Summary of Deposits (county share); HMDA mortgage data; county permits & deed records | H91: Unverified | I91: 2 | J91: 3 | K91: =IF(C91>=50,1,0) -> 1 | L91: =IF(H91="0 (checked)",2,IF(H91="Unverified",1,IF(H91="1 (checked)",0.5,0))) -> 1 | M91: =I91+J91+K91+L91 -> 7 | N91: =IF(C91<25,"Nano (<$25M)",IF(C91<100,"$25-100M",IF(C91<250,"$100-250M","$250-500M"))) -> $250-500M
... A95: ISBA | B95: Isabella Bank | C95: 296.84 | D95: Community bank | E95: Loan growth, deposits and credit tied to one local economy and its real estate | F95: FFIEC call reports (quarterly, bank-level); FDIC Summary of Deposits (county share); HMDA mortgage data; county permits & deed records | H95: Unverified | I95: 2 | J95: 3 | K95: =IF(C95>=50,1,0) -> 1 | L95: =IF(H95="0 (checked)",2,IF(H95="Unverified",1,IF(H95="1 (checked)",0.5,0))) -> 1 | M95: =I95+J95+K95+L95 -> 7 | N95: =IF(C95<25,"Nano (<$25M)",IF(C95<100,"$25-100M",IF(C95<250,"$100-250M","$250-500M"))) -> $250-500M
A96: TII | B96: Titan Mining | C96: 295.07 | D96: Mine developer / producer | E96: State mine, water and air permits plus county approvals gate the project | F96: State environmental agency permit dockets; county commission agendas; state mining reports | G96: Upstate New York zinc/graphite | H96: Unverified | I96: 3 | J96: 2 | K96: =IF(C96>=50,1,0) -> 1 | L96: =IF(H96="0 (checked)",2,IF(H96="Unverified",1,IF(H96="1 (checked)",0.5,0))) -> 1 | M96: =I96+J96+K96+L96 -> 7 | N96: =IF(C96<25,"Nano (<$25M)",IF(C96<100,"$25-100M",IF(C96<250,"$100-250M","$250-500M"))) -> $250-500M
A97: ALCO | B97: Alico | C97: 289.84 | D97: Land / entitlement developer | E97: Value unlocked by entitlements, zoning, plats and permits on specific parcels | F97: Planning commission & council agendas; plat approvals; Census BPS; county deed and assessor records | G97: Collier County approvals; 2 analysts (Roth, Freedom) - fails strict zero screen | H97: 2+ (checked) | I97: 3 | J97: 3 | K97: =IF(C97>=50,1,0) -> 1 | L97: =IF(H97="0 (checked)",2,IF(H97="Unverified",1,IF(H97="1 (checked)",0.5,0))) -> 0 | M97: =I97+J97+K97+L97 -> 7 | N97: =IF(C97<25,"Nano (<$25M)",IF(C97<100,"$25-100M",IF(C97<250,"$100-250M","$250-500M"))) -> $250-500M
A98: CDZI | B98: Cadiz | C98: 289.6 | D98: Energy project developer | E98: County zoning/siting votes and state incentive programs decide whether projects get built | F98: County zoning agendas (siting moratoriums); state program dockets (community solar, LCFS); interconnection queues | G98: California water project - state/county approvals | H98: Unverified | I98: 3 | J98: 2 | K98: =IF(C98>=50,1,0) -> 1 | L98: =IF(H98="0 (checked)",2,IF(H98="Unverified",1,IF(H98="1 (checked)",0.5,0))) -> 1 | M98: =I98+J98+K98+L98 -> 7 | N98: =IF(C98<25,"Nano (<$25M)",IF(C98<100,"$25-100M",IF(C98<250,"$100-250M","$250-500M"))) -> $250-500M
A99: GBFH | B99: GBank Financial Holdings | C99: 289.31 | D99: Community bank | E99: Loan growth, deposits and credit tied to one local economy and its real estate | F99: FFIEC call reports (quarterly, bank-level); FDIC Summary of Deposits (county share); HMDA mortgage data; county permits & deed records | H99: Unverified | I99: 2 | J99: 3 | K99: =IF(C99>=50,1,0) -> 1 | L99: =IF(H99="0 (checked)",2,IF(H99="Unverified",1,IF(H99="1 (checked)",0.5,0))) -> 1 | M99: =I99+J99+K99+L99 -> 7 | N99: =IF(C99<25,"Nano (<$25M)",IF(C99<100,"$25-100M",IF(C99<250,"$100-250M","$250-500M"))) -> $250-500M
A100: OVLY | B100: Oak Valley Bancorp | C100: 286.69 | D100: Community bank | E100: Loan growth, deposits and credit tied to one local economy and its real estate | F100: FFIEC call reports (quarterly, bank-level); FDIC Summary of Deposits (county share); HMDA mortgage data; county permits & deed records | H100: Unverified | I100: 2 | J100: 3 | K100: =IF(C100>=50,1,0) -> 1 | L100: =IF(H100="0 (checked)",2,IF(H100="Unverified",1,IF(H100="1 (checked)",0.5,0))) -> 1 | M100: =I100+J100+K100+L100 -> 7 | N100: =IF(C100<25,"Nano (<$25M)",IF(C100<100,"$25-100M",IF(C100<250,"$100-250M","$250-500M"))) -> $250-500M
A101: FUNC | B101: First United Corp | C101: 286.55 | D101: Community bank | E101: Loan growth, deposits and credit tied to one local economy and its real estate | F101: FFIEC call reports (quarterly, bank-level); FDIC Summary of Deposits (county share); HMDA mortgage data; county permits & deed records | H101: Unverified | I101: 2 | J101: 3 | K101: =IF(C101>=50,1,0) -> 1 | L101: =IF(H101="0 (checked)",2,IF(H101="Unverified",1,IF(H101="1 (checked)",0.5,0))) -> 1 | M101: =I101+J101+K101+L101 -> 7 | N101: =IF(C101<25,"Nano (<$25M)",IF(C101<100,"$25-100M",IF(C101<250,"$100-250M","$250-500M"))) -> $250-500M
A102: ATLO | B102: Ames National | C102: 286.44 | D102: Community bank | E102: Loan growth, deposits and credit tied to one local economy and its real estate | F102: FFIEC call reports (quarterly, bank-level); FDIC Summary of Deposits (county share); HMDA mortgage data; county permits & deed records | H102: Unverified | I102: 2 | J102: 3 | K102: =IF(C102>=50,1,0) -> 1 | L102: =IF(H102="0 (checked)",2,IF(H102="Unverified",1,IF(H102="1 (checked)",0.5,0))) -> 1 | M102: =I102+J102+K102+L102 -> 7 | N102: =IF(C102<25,"Nano (<$25M)",IF(C102<100,"$25-100M",IF(C102<250,"$100-250M","$250-500M"))) -> $250-500M
A103: FRAF | B103: Franklin Financial Services | C103: 284.73 | D103: Community bank | E103: Loan growth, deposits and credit tied to one local economy and its real estate | F103: FFIEC call reports (quarterly, bank-level); FDIC Summary of Deposits (county share); HMDA mortgage data; county permits & deed records | H103: Unverified | I103: 2 | J103: 3 | K103: =IF(C103>=50,1,0) -> 1 | L103: =IF(H103="0 (checked)",2,IF(H103="Unverified",1,IF(H103="1 (checked)",0.5,0))) -> 1 | M103: =I103+J103+K103+L103 -> 7 | N103: =IF(C103<25,"Nano (<$25M)",IF(C103<100,"$25-100M",IF(C103<250,"$100-250M","$250-500M"))) -> $250-500M
A104: FNRN | B104: First Northern Community Bancorp | C104: 283.15 | D104: Community bank | E104: Loan growth, deposits and credit tied to one local economy and its real estate | F104: FFIEC call reports (quarterly, bank-level); FDIC Summary of Deposits (county share); HMDA mortgage data; county permits & deed records | H104: Unverified | I104: 2 | J104: 3 | K104: =IF(C104>=50,1,0) -> 1 | L104: =IF(H104="0 (checked)",2,IF(H104="Unverified",1,IF(H104="1 (checked)",0.5,0))) -> 1 | M104: =I104+J104+K104+L104 -> 7 | N104: =IF(C104<25,"Nano (<$25M)",IF(C104<100,"$25-100M",IF(C104<250,"$100-250M","$250-500M"))) -> $250-500M
...

Sheet Archetypes
A1: Archetypes - what drives each group and which public data the platform ingests
A3: Archetype | B3: Local-gov driver | C3: Public data to ingest | D3: Local-gov intensity | E3: Data edge
A4: Community bank | B4: Loan growth, deposits and credit tied to one local economy and its real estate | C4: FFIEC call reports (quarterly, bank-level); FDIC Summary of Deposits (county share); HMDA mortgage data; county permits & deed records | D4: 2 | E4: 3
A5: Regulated utility | B5: State commission sets rates; customer additions come from local development approvals | C5: State PUC/SCC rate dockets; county subdivision approvals; Census Building Permits Survey | D5: 3 | E5: 2
A6: Energy project developer | B6: County zoning/siting votes and state incentive programs decide whether projects get built | C6: County zoning agendas (siting moratoriums); state program dockets (community solar, LCFS); interconnection queues | D6: 3 | E6: 2
A7: Land / entitlement developer | B7: Value unlocked by entitlements, zoning, plats and permits on specific parcels | C7: Planning commission & council agendas; plat approvals; Census BPS; county deed and assessor records | D7: 3 | E7: 3
A8: Property owner (commercial) | B8: Asset values and leasing in a handful of metros; zoning and property-tax decisions | C8: County assessor/recorder data; local building permits; zoning/rezoning agendas | D8: 2 | E8: 2
A9: Apartment owner | B9: Rents shaped by local rent rules and new-supply permits in specific metros | C9: Local rent boards (e.g., NYC Rent Guidelines Board); multifamily permits; eviction filings; property-tax assessments | D9: 3 | E9: 3
A10: RE transaction platform | B10: Revenue tracks home/commercial transaction counts in specific markets | C10: County deed recordings (e.g., NYC ACRIS); transfer-tax receipts; MLS-derived counts | D10: 1 | E10: 3
A11: Hotel owner | B11: Local hotel demand, convention calendars, city policy | C11: City hotel/occupancy-tax reports; convention-center calendars; local permits | D11: 2 | E11: 3
A12: Farmland / water rights | B12: Water rights, county ag zoning and land conversion approvals | C12: State water-rights filings & allocations; USDA land values; county records | D12: 2 | E12: 2
A13: Regional gaming / racing | B13: State gaming & racing commissions license and tax; local approvals for expansions | C13: Monthly state gaming-revenue reports by property; racing commission minutes; city development agendas | D13: 3 | E13: 3
A14: Oil & gas producer / royalty | B14: Production, permits and spacing on specific acreage set by state regulators | C14: State oil & gas commission well permits & monthly production (Texas RRC, NM OCD, Oklahoma OCC, Louisiana SONRIS, etc.) | D14: 2 | E14: 3
A15: Midstream / energy infrastructure | B15: State/local permits and government supply contracts | C15: State permit dockets; utility/government contract awards; port authority agendas | D15: 2 | E15: 2
... A22: Government-funded services | B22: State/municipal contracts, subsidies and licensing | C22: Municipal contract registers (e.g., NYC Checkbook); state subsidy rate schedules; licensing boards | D22: 3 | E22: 2

Sheet Excluded
A1: Screened out of the industry lists, and why
A3: Reason | B3: Examples
A4: Foreign operations / domicile | B4: e.g., ELLO, WAVE, HTOO, LPA, LND, GTE, NRT, ANNA, MSC, CVEO, ATLX, most China/HK/Singapore-based listings in education, construction and real estate
A5: Canadian/foreign mine juniors | B5: e.g., NMG, PHOS, LZM, GRO, VGZ, TRX, CMCL, FURY, GLDG - permits sit outside US local government
A6: Consumer / tech with no local-gov link | B6: e.g., leisure brands, Chegg, Skillsoft, Gogo, Cogent, most 'renewable' microcap startups
A7: Above $500M | B7: e.g., YORW ($502M) just misses - consider raising the cap to $750M in v2
A8: Liquidating / delisting | B8: STRS (plan of liquidation, intends to delist) - GYRO and SRG kept because entitlements drive their liquidation value
A9: Status unclear | B9: GREE (Greenidge) - no current listing data found; verify name/ticker before adding

Sheet Method
A1: Method, scoring and caveats
A3: 1. Universe: StockAnalysis.com industry pages (pulled Oct 16, 2026) for ~30 industries where local or state government is a plausible driver: regional banks, utilities, real estate & REITs, land, construction, waste, gaming, lodging, farmland, oil & gas, midstream, mining, telecom, P&C insurance, healthcare facilities, education.
A4: 2. Filter: market cap below $500M, US operations, not a shell. Archetype assigned by industry plus company knowledge; notes added where a specific local body or dataset is known.
A5: 3. Priority = Local-gov intensity (1-3) + Data edge (1-3) + Tradable (1 if >= $50M) + Coverage points (2 if verified zero, 1 if unverified, 0.5 if one analyst, 0 if two or more). Max 9. Intensity and data-edge scores are judgment calls set per archetype on the Archetypes tab - edit them there in the build or override per row.
A6: 4. Coverage: only 14 names are verified so far. Run coverage_check.py on your own computer (it uses Yahoo Finance via the yfinance package) to fill column H for every name; Priority recalculates automatically. Confirm zero-coverage names on Bloomberg (ANR) or CapIQ before saying 'uncovered' in print - free sources miss single-broker coverage.
A7: 5. Expect many community banks to have 1-3 regional-broker analysts (Janney, Hovde, Piper, KBW, Stephens, DA Davidson). They stay in the universe because call-report and deposit data are a real edge even with light coverage.
A8: 6. Market caps are as of Oct 16, 2026 and will drift. A few figures look off (e.g., CABO, WHLR) and are flagged in the Note column - check before use.
A9: 7. Not yet included: OTC-traded companies (likely several hundred more zero-coverage names: community banks, small utilities, land companies), and NYSE/Nasdaq names in industries not pulled here. Adding OTC is the obvious v2.
